create2/__init__.py
create2/contracts/Create2Factory.sol
create2/exceptions.py
create2-0.1.1.dist-info/METADATA
create2-0.1.1.dist-info/WHEEL
create2-0.1.1.dist-info/RECORD
