Metadata-Version: 2.1
Name: create2
Version: 0.1.1
Summary: Web3 create2.
License: MIT
Author: 0xgustavo
Author-email: 0xgustavo@proton.me
Requires-Python: >=3.12,<4.0
Classifier: License :: OSI Approved :: MIT License
Classifier: Programming Language :: Python :: 3
Classifier: Programming Language :: Python :: 3.12
Requires-Dist: web3 (>=6.14.0,<7.0.0)
